zix/__init__.py
zix/__main__.py
zix/cli.py
zix/default_project/Dockerfile
zix/default_project/alembic.ini
zix/default_project/env.yml
zix/default_project/requirements.txt
zix/default_project/requirements_dev.txt
zix/default_project/alembic/README
zix/default_project/alembic/env.py
zix/default_project/alembic/script.py.mako
zix/default_project/alembic/versions/.zixkeep
zix/default_project/app/__init__.py
zix/default_project/app/config/__init__.py
zix/default_project/app/config/common.py
zix/default_project/app/config/local.py
zix/default_project/app/config/server.py
zix/default_project/app/external/__init__.py
zix/default_project/app/external/stripe.py
zix/default_project/app/plugins/__init__.py
zix/default_project/app/plugins/auth/__init__.py
zix/default_project/app/plugins/auth/crud.py
zix/default_project/app/plugins/auth/models.py
zix/default_project/app/plugins/auth/routers.py
zix/default_project/app/plugins/auth/schemas.py
zix/default_project/app/plugins/plugin_template/.zixignore
zix/default_project/app/plugins/plugin_template/__init__.py
zix/default_project/app/plugins/plugin_template/crud.py
zix/default_project/app/plugins/plugin_template/models.py
zix/default_project/app/plugins/plugin_template/routers.py
zix/default_project/app/plugins/plugin_template/schemas.py
zix/default_project/app/plugins/subscriptions/__init__.py
zix/default_project/app/plugins/subscriptions/crud.py
zix/default_project/app/plugins/subscriptions/models.py
zix/default_project/app/plugins/subscriptions/routers.py
zix/default_project/app/plugins/subscriptions/schemas.py
zix/default_project/app/plugins/users/__init__.py
zix/default_project/app/plugins/users/crud.py
zix/default_project/app/plugins/users/models.py
zix/default_project/app/plugins/users/routers.py
zix/default_project/app/plugins/users/schemas.py
zix/default_project/app/plugins/web/__init__.py
zix/default_project/app/plugins/web/routers.py
zix/default_project/app/plugins/web/schemas.py
zixweb-0.1.9.dist-info/LICENSE
zixweb-0.1.9.dist-info/METADATA
zixweb-0.1.9.dist-info/WHEEL
zixweb-0.1.9.dist-info/entry_points.txt
zixweb-0.1.9.dist-info/top_level.txt
zixweb-0.1.9.dist-info/RECORD
