Metadata-Version: 2.1
Name: zixweb
Version: 0.1.9
Summary: zix - Create your SaaS app quickly by adding plugins!
Home-page: https://github.com/anelendata/zix
Author: Daigo Tanaka, Anelen Co., LLC
Classifier: Development Status :: 2 - Pre-Alpha
Classifier: License :: OSI Approved :: Apache Software License
Classifier: Operating System :: MacOS :: MacOS X
Classifier: Operating System :: POSIX :: Linux
Classifier: Programming Language :: Python :: 3.8
Classifier: Programming Language :: Python :: 3.9
Classifier: Programming Language :: Python :: 3.10
Classifier: Programming Language :: Python :: 3.11
License-File: LICENSE
Requires-Dist: Authlib==0.15.3
Requires-Dist: fastapi==0.95.1
Requires-Dist: httpx==0.27.2
Requires-Dist: itsdangerous==2.1.2
Requires-Dist: python-jose==3.3.0
Requires-Dist: PyYAML==6.0
Requires-Dist: requests==2.32.3
Requires-Dist: six==1.16.0
Requires-Dist: SQLAlchemy==2.0.33
Requires-Dist: SQLAlchemy-Utils==0.41.2
Requires-Dist: starlette-context==0.3.6
Requires-Dist: uvicorn==0.22.0
